LICENSE
MANIFEST.in
README.rst
requirements.txt
run-mpitests.py
setup.cfg
setup.py
test_requirements.txt
examples/command_line_problems/bin_packing.py
examples/command_line_problems/binary_knapsack.py
examples/command_line_problems/lipschitz_1d.py
examples/command_line_problems/rosenbrock_2d.py
examples/scripts/range_reduction_pyomo.py
examples/scripts/simple.py
examples/scripts/tsp/fri26_d.txt
examples/scripts/tsp/p01_d.txt
examples/scripts/tsp/p01_d_inf.txt
examples/scripts/tsp/tsp_byedge.py
examples/scripts/tsp/tsp_byvertex.py
examples/scripts/tsp/tsp_util.py
src/pybnb/__about__.py
src/pybnb/__init__.py
src/pybnb/common.py
src/pybnb/configuration.py
src/pybnb/convergence_checker.py
src/pybnb/dispatcher.py
src/pybnb/dispatcher_proxy.py
src/pybnb/futures.py
src/pybnb/misc.py
src/pybnb/mpi_utils.py
src/pybnb/node.py
src/pybnb/priority_queue.py
src/pybnb/problem.py
src/pybnb/solver.py
src/pybnb/solver_results.py
src/pybnb.egg-info/PKG-INFO
src/pybnb.egg-info/SOURCES.txt
src/pybnb.egg-info/dependency_links.txt
src/pybnb.egg-info/requires.txt
src/pybnb.egg-info/top_level.txt
src/pybnb/pyomo/__init__.py
src/pybnb/pyomo/misc.py
src/pybnb/pyomo/problem.py
src/pybnb/pyomo/range_reduction.py
src/tests/__init__.py
src/tests/test_common.py
src/tests/test_configuration.py
src/tests/test_convergence_checker.py
src/tests/test_dispatcher.py
src/tests/test_examples.py
src/tests/test_misc.py
src/tests/test_node.py
src/tests/test_package.py
src/tests/test_priority_queue.py
src/tests/test_problem.py
src/tests/test_solver.py
src/tests/test_solver_results.py
src/tests/test_tsp.py
src/tests/example_baselines/bin_packing.yaml
src/tests/example_baselines/binary_knapsack.yaml
src/tests/example_baselines/lipschitz_1d.yaml
src/tests/example_baselines/range_reduction_pyomo.yaml
src/tests/example_baselines/rosenbrock_2d.yaml
src/tests/example_baselines/tsp_byedge_p01_d.yaml
src/tests/example_baselines/tsp_byedge_p01_d_inf.yaml
src/tests/example_baselines/tsp_byvertex_p01_d.yaml
src/tests/example_baselines/tsp_byvertex_p01_d_inf.yaml
src/tests/mpi/__init__.py
src/tests/mpi/common.py
src/tests/mpi/test_futures.py
src/tests/mpi/test_heaps.py
