Metadata-Version: 1.1
Name: pybnb
Version: 0.6.1
Summary: A parallel branch-and-bound engine for Python
Home-page: https://github.com/ghackebeil/pybnb
Author: Gabriel A. Hackebeil
Author-email: gabe.hackebeil@gmail.com
License: MIT
Keywords: optimization,branch and bound
Platform: UNKNOWN
Classifier: Development Status :: 4 - Beta
Classifier: Intended Audience :: Science/Research
Classifier: Topic :: Scientific/Engineering :: Mathematics
Classifier: Natural Language :: English
Classifier: License :: OSI Approved :: MIT License
Classifier: Programming Language :: Python :: 2.7
Classifier: Programming Language :: Python :: 3
Classifier: Programming Language :: Python :: 3.5
Classifier: Programming Language :: Python :: 3.6
Classifier: Programming Language :: Python :: 3.7
Classifier: Programming Language :: Python :: Implementation :: CPython
Classifier: Programming Language :: Python :: Implementation :: PyPy
